[
    {
        "nombre": "Rafael Muñoz Guardia",
        "equipo": "Joanfran Albolote",
        "goles": 12,
        "avatar": "https://minifootballleagues.com/upload/44/28/kcn3ewa3.jpg"
    },
    {
        "nombre": "** Daniel Guijarro Torres",
        "equipo": "Celtic Pulianas",
        "goles": 12,
        "avatar": "https://minifootballleagues.com/upload/24/90/td3uzzlc.jpg"
    },
    {
        "nombre": "** Fernando Fernández Espínola",
        "equipo": "Atlético La Zubia",
        "goles": 8,
        "avatar": "https://minifootballleagues.com/upload/D5/2A/xsb4mjea.jpg"
    },
    {
        "nombre": "Pablo Martinez  Lao",
        "equipo": "Celtic Pulianas",
        "goles": 7,
        "avatar": "https://minifootballleagues.com/upload/imagesv2/avatars/Avatar_Ball_01.png"
    },
    {
        "nombre": "Moisés  Gómez Moreno",
        "equipo": "Joanfran Albolote",
        "goles": 7,
        "avatar": "https://minifootballleagues.com/upload/imagesv2/avatars/OliverAtom 1.png"
    },
    {
        "nombre": "Richard  López Zapata",
        "equipo": "Joanfran Albolote",
        "goles": 7,
        "avatar": "https://minifootballleagues.com/upload/3A/C8/vjjchjj5.jpg"
    },
    {
        "nombre": "José Prieto Peralta",
        "equipo": "Joanfran Albolote",
        "goles": 6,
        "avatar": "https://minifootballleagues.com/upload/D2/07/4crhnwyp.jpg"
    },
    {
        "nombre": "Manuel Sánchez Fernández",
        "equipo": "Monachil",
        "goles": 6,
        "avatar": "https://minifootballleagues.com/upload/16/D4/b2wphlfx.jpg"
    },
    {
        "nombre": "José Fernández Cantarero",
        "equipo": "Monachil",
        "goles": 5,
        "avatar": "https://minifootballleagues.com/upload/imagesv2/avatars/Avatar_Ball_04.png"
    },
    {
        "nombre": "Alfredo Quedada Izquierdo",
        "equipo": "Churriana",
        "goles": 5,
        "avatar": "https://minifootballleagues.com/upload/0C/F8/vk2tun12.jpg"
    },
    {
        "nombre": "** Miguel Pérez Domínguez",
        "equipo": "Ogijares 89 Fc",
        "goles": 5,
        "avatar": "https://minifootballleagues.com/upload/imagesv2/avatars/image 3003.png"
    },
    {
        "nombre": "Manuel Pérez Malagón",
        "equipo": "Peña Fútbol Villanueva Mesia",
        "goles": 5,
        "avatar": "https://minifootballleagues.com/upload/9B/A5/1vpfwdjr.jpg"
    },
    {
        "nombre": "** Daniel Sampedro Fuentes",
        "equipo": "Atlético La Zubia",
        "goles": 5,
        "avatar": "https://minifootballleagues.com/upload/D4/6E/wmrpm2zg.jpg"
    },
    {
        "nombre": "Zakaría El Hadi",
        "equipo": "Churriana",
        "goles": 4,
        "avatar": "https://minifootballleagues.com/upload/79/50/3hy4web2.jpg"
    },
    {
        "nombre": "** Javier  Tallon Jimenez",
        "equipo": "Churriana",
        "goles": 4,
        "avatar": "https://minifootballleagues.com/upload/48/6E/p50af41g.jpg"
    },
    {
        "nombre": "José pablo Labella Jiménez",
        "equipo": "Joanfran Albolote",
        "goles": 4,
        "avatar": "https://minifootballleagues.com/upload/imagesv2/avatars/Kubala.png"
    },
    {
        "nombre": "Juan Ramón Vílchez Martín",
        "equipo": "Ogijares 89 Fc",
        "goles": 4,
        "avatar": "https://minifootballleagues.com/upload/imagesv2/avatars/Avatar_Ball_04.png"
    },
    {
        "nombre": "Oscar García Guerrero",
        "equipo": "Atlético La Zubia",
        "goles": 3,
        "avatar": "https://minifootballleagues.com/upload/9C/C0/bny4xdrs.jpg"
    },
    {
        "nombre": "Ángel  Martín Navarro",
        "equipo": "Churriana",
        "goles": 3,
        "avatar": "https://minifootballleagues.com/upload/3E/47/s1raihr0.jpg"
    },
    {
        "nombre": "** Rubén Cuadros Criado",
        "equipo": "Ogijares 89 Fc",
        "goles": 3,
        "avatar": "https://minifootballleagues.com/static/user/default5.png"
    },
    {
        "nombre": "Angel Molinero Rivas",
        "equipo": "Churriana",
        "goles": 3,
        "avatar": "https://minifootballleagues.com/upload/imagesv2/avatars/OliverAtom 1.png"
    },
    {
        "nombre": "Rafael Sánchez Ramírez",
        "equipo": "Joanfran Albolote",
        "goles": 3,
        "avatar": "https://minifootballleagues.com/upload/F4/0D/sdyur4js.jpg"
    },
    {
        "nombre": "Isidro Piteño Domínguez",
        "equipo": "Atlético La Zubia",
        "goles": 3,
        "avatar": "https://minifootballleagues.com/upload/B8/A7/5ea1mc01.jpg"
    },
    {
        "nombre": "Mario Gómez Cebrián",
        "equipo": "Atlético La Zubia",
        "goles": 3,
        "avatar": "https://minifootballleagues.com/upload/F3/94/jcu5zpqc.jpg"
    },
    {
        "nombre": "Pedro Adróver Pérez",
        "equipo": "Ogijares 89 Fc",
        "goles": 3,
        "avatar": "https://minifootballleagues.com/upload/imagesv2/avatars/Maradona.png"
    },
    {
        "nombre": "Jose Maria Siles Agudo",
        "equipo": "Celtic Pulianas",
        "goles": 3,
        "avatar": "https://minifootballleagues.com/upload/imagesv2/avatars/image 3003.png"
    },
    {
        "nombre": "Antonio Fernandez Gomez",
        "equipo": "Celtic Pulianas",
        "goles": 3,
        "avatar": "https://minifootballleagues.com/static/user/default6.png"
    },
    {
        "nombre": "Jorge Romero Rodríguez",
        "equipo": "Ogijares 89 Fc",
        "goles": 3,
        "avatar": "https://minifootballleagues.com/upload/79/27/iw14swhn.jpg"
    },
    {
        "nombre": "Víctor Manuel  Martín Bailón",
        "equipo": "Joanfran Albolote",
        "goles": 3,
        "avatar": "https://minifootballleagues.com/upload/5F/6C/vm2hpiit.jpg"
    },
    {
        "nombre": "Francisco Javier  Cardenete Garcia",
        "equipo": "Peña Fútbol Villanueva Mesia",
        "goles": 3,
        "avatar": "https://minifootballleagues.com/upload/34/74/npy4mrdo.jpg"
    },
    {
        "nombre": "Manuel Gamiz Matas",
        "equipo": "Peña Fútbol Villanueva Mesia",
        "goles": 3,
        "avatar": "https://minifootballleagues.com/upload/31/BD/xc55ctle.jpg"
    },
    {
        "nombre": "Ivan Gómez Fernandez",
        "equipo": "Celtic Pulianas",
        "goles": 2,
        "avatar": "https://minifootballleagues.com/upload/0D/9F/vvjzaawk.jpg"
    },
    {
        "nombre": "Miguel Montoya Hidalgo",
        "equipo": "Atlético La Zubia",
        "goles": 2,
        "avatar": "https://minifootballleagues.com/upload/88/C9/tghmhouk.jpg"
    },
    {
        "nombre": "José Manuel Espigares Balboa",
        "equipo": "Ogijares 89 Fc",
        "goles": 2,
        "avatar": "https://minifootballleagues.com/upload/imagesv2/avatars/Avatar_Ball_04.png"
    },
    {
        "nombre": "Elías Prieto Crespo",
        "equipo": "Otura",
        "goles": 2,
        "avatar": "https://minifootballleagues.com/upload/41/C8/2cgr0xs4.jpg"
    },
    {
        "nombre": "Jose Manuel Morales Solera",
        "equipo": "Churriana",
        "goles": 2,
        "avatar": "https://minifootballleagues.com/upload/imagesv2/avatars/image 3005.png"
    },
    {
        "nombre": "José Manuel López Ruiz",
        "equipo": "Otura",
        "goles": 2,
        "avatar": "https://minifootballleagues.com/upload/imagesv2/avatars/OliverAtom 1.png"
    },
    {
        "nombre": "Alberto Jiménez Carrasco",
        "equipo": "Joanfran Albolote",
        "goles": 2,
        "avatar": "https://minifootballleagues.com/upload/5C/6F/e15y424r.jpg"
    },
    {
        "nombre": "Rafael Iáñez Béjar",
        "equipo": "Atlético La Zubia",
        "goles": 2,
        "avatar": "https://minifootballleagues.com/upload/48/94/tx2xpi53.jpg"
    },
    {
        "nombre": "Manuel Cuadros Roldán",
        "equipo": "Otura",
        "goles": 2,
        "avatar": "https://minifootballleagues.com/upload/imagesv2/avatars/OliverAtom 1.png"
    },
    {
        "nombre": "Enrique  Fernández López",
        "equipo": "Joanfran Albolote",
        "goles": 2,
        "avatar": "https://minifootballleagues.com/upload/imagesv2/avatars/Avatar_Ball_01.png"
    },
    {
        "nombre": "Dani Garcia Jiménez",
        "equipo": "Monachil",
        "goles": 2,
        "avatar": "https://minifootballleagues.com/upload/0D/EE/ydsddz5j.jpg"
    },
    {
        "nombre": "Adrián Iglesias Martínez",
        "equipo": "Joanfran Albolote",
        "goles": 2,
        "avatar": "https://minifootballleagues.com/upload/7E/6F/sf2vwrxs.jpg"
    },
    {
        "nombre": "Antonio Raúl  Tojar Gordo",
        "equipo": "Joanfran Albolote",
        "goles": 2,
        "avatar": "https://minifootballleagues.com/static/user/default4.png"
    },
    {
        "nombre": "Darío López Padial",
        "equipo": "Ogijares 89 Fc",
        "goles": 2,
        "avatar": "https://minifootballleagues.com/upload/5E/CF/nrj14c0y.jpg"
    },
    {
        "nombre": "Antonio \"Luján\" Fernández Hervás",
        "equipo": "Ogijares 89 Fc",
        "goles": 2,
        "avatar": "https://minifootballleagues.com/upload/AF/C1/jwijfw3s.jpg"
    },
    {
        "nombre": "Enrique Osuna López",
        "equipo": "Churriana",
        "goles": 1,
        "avatar": "https://minifootballleagues.com/static/user/default3.png"
    },
    {
        "nombre": "Daniel González Benítez",
        "equipo": "Ogijares 89 Fc",
        "goles": 1,
        "avatar": "https://minifootballleagues.com/upload/imagesv2/avatars/Avatar_Warrior_05.png"
    },
    {
        "nombre": "** Javier  Pérez Cobos",
        "equipo": "Peña Fútbol Villanueva Mesia",
        "goles": 1,
        "avatar": "https://minifootballleagues.com/upload/9B/D3/z1yav3ed.jpg"
    },
    {
        "nombre": "** Adrián  Tenorio Rodríguez",
        "equipo": "Joanfran Albolote",
        "goles": 1,
        "avatar": "https://minifootballleagues.com/upload/A1/87/wq5hbxb3.jpg"
    },
    {
        "nombre": "** José Manuel  Aguilera Molina",
        "equipo": "Peña Fútbol Villanueva Mesia",
        "goles": 1,
        "avatar": "https://minifootballleagues.com/upload/6A/B2/0qv4ctfm.jpg"
    },
    {
        "nombre": "Karim A.",
        "equipo": "Celtic Pulianas",
        "goles": 1,
        "avatar": "https://minifootballleagues.com/upload/3B/C9/d5ul3oft.jpg"
    },
    {
        "nombre": "Gerardo  Leyva Lopez",
        "equipo": "Peña Fútbol Villanueva Mesia",
        "goles": 1,
        "avatar": "https://minifootballleagues.com/static/user/default5.png"
    },
    {
        "nombre": "José Antonio Serrano García",
        "equipo": "Atlético La Zubia",
        "goles": 1,
        "avatar": "https://minifootballleagues.com/upload/ED/35/dnpvm0r4.jpg"
    },
    {
        "nombre": "Alberto Millan Solano",
        "equipo": "Celtic Pulianas",
        "goles": 1,
        "avatar": "https://minifootballleagues.com/upload/3B/C3/vnwzkcge.jpg"
    },
    {
        "nombre": "Francisco Jesús  Huertas Pérez",
        "equipo": "Monachil",
        "goles": 1,
        "avatar": "https://minifootballlleaguesalmeria.mygol.es/upload/imagesv2/avatars/Avatar_Ball_04.png"
    },
    {
        "nombre": "Francisco García Guerrero",
        "equipo": "Atlético La Zubia",
        "goles": 1,
        "avatar": "https://minifootballleagues.com/upload/imagesv2/avatars/Avatar_Animal_02.png"
    },
    {
        "nombre": "Antonio Morente Valero",
        "equipo": "Churriana",
        "goles": 1,
        "avatar": "https://minifootballleagues.com/upload/imagesv2/avatars/Avatar_Ball_04.png"
    },
    {
        "nombre": "Vicente Ortega Estepa",
        "equipo": "Ogijares 89 Fc",
        "goles": 1,
        "avatar": "https://minifootballleagues.com/static/user/default3.png"
    },
    {
        "nombre": "Francisco Javier Morente Guzmán",
        "equipo": "Otura",
        "goles": 1,
        "avatar": "https://minifootballleagues.com/upload/imagesv2/avatars/image 3004.png"
    },
    {
        "nombre": "** Sergio Guerrero de la Camara",
        "equipo": "Celtic Pulianas",
        "goles": 1,
        "avatar": "https://minifootballleagues.com/upload/69/B5/xzt2ty5k.jpg"
    },
    {
        "nombre": "Manuel Fernandez Puente",
        "equipo": "Celtic Pulianas",
        "goles": 1,
        "avatar": "https://minifootballleagues.com/upload/imagesv2/avatars/Avatar_Player_09.png"
    },
    {
        "nombre": "Jose Antonio Diaz Muñoz",
        "equipo": "Celtic Pulianas",
        "goles": 1,
        "avatar": "https://minifootballleagues.com/upload/B6/B5/gdd2huc2.jpg"
    },
    {
        "nombre": "** Aitor Rodriguez Hernandez",
        "equipo": "Celtic Pulianas",
        "goles": 1,
        "avatar": "https://minifootballleagues.com/static/user/default1.png"
    },
    {
        "nombre": "Jaime Carrasco Cabrera ***",
        "equipo": "Otura",
        "goles": 1,
        "avatar": "https://minifootballleagues.com/static/user/default3.png"
    },
    {
        "nombre": "José Ángel Carmona Sánchez",
        "equipo": "Otura",
        "goles": 1,
        "avatar": "https://minifootballleagues.com/upload/76/68/dpwbknzr.jpg"
    },
    {
        "nombre": "Antonio Jesús García García",
        "equipo": "Otura",
        "goles": 1,
        "avatar": "https://minifootballleagues.com/upload/7A/E2/xavatlbr.jpg"
    },
    {
        "nombre": "Gonzalo Medina Talero",
        "equipo": "Joanfran Albolote",
        "goles": 1,
        "avatar": "https://minifootballleagues.com/upload/FC/37/5as1bqai.jpg"
    },
    {
        "nombre": "** Juan Carlos  Lopez Muñoz",
        "equipo": "Joanfran Albolote",
        "goles": 1,
        "avatar": "https://minifootballleagues.com/upload/96/D4/rvh3pm3j.jpg"
    },
    {
        "nombre": "Raúl Salvago García",
        "equipo": "Churriana",
        "goles": 1,
        "avatar": "https://minifootballleagues.com/upload/imagesv2/avatars/Avatar_Ball_04.png"
    },
    {
        "nombre": "Raul López Escamilla",
        "equipo": "Peña Fútbol Villanueva Mesia",
        "goles": 1,
        "avatar": "https://minifootballleagues.com/static/user/default1.png"
    },
    {
        "nombre": "Isaac Úbeda Fernández",
        "equipo": "Otura",
        "goles": 1,
        "avatar": "https://minifootballleagues.com/upload/imagesv2/avatars/Maradona.png"
    },
    {
        "nombre": "** Miguel Angel Fajardo Aguado",
        "equipo": "Monachil",
        "goles": 1,
        "avatar": "https://minifootballleagues.com/upload/D4/57/osg5vvsy.jpg"
    },
    {
        "nombre": "Juan Gallego Martín",
        "equipo": "Monachil",
        "goles": 1,
        "avatar": "https://minifootballleagues.com/upload/8C/30/zlf3afo2.jpg"
    },
    {
        "nombre": "Francisco José Martínez Sánchez",
        "equipo": "Celtic Pulianas",
        "goles": 1,
        "avatar": "https://minifootballleagues.com/upload/imagesv2/avatars/Avatar_Shoe_03.png"
    },
    {
        "nombre": "José Francisco Quesada García",
        "equipo": "Atlético La Zubia",
        "goles": 1,
        "avatar": "https://minifootballleagues.com/upload/02/1D/oeex1kb3.jpg"
    },
    {
        "nombre": "Juan de Dios Aguilera Sánchez",
        "equipo": "Atlético La Zubia",
        "goles": 1,
        "avatar": "https://minifootballleagues.com/static/user/default3.png"
    },
    {
        "nombre": "Jose Antonio \"Ñoño\" Jiménez Muñoz",
        "equipo": "Ogijares 89 Fc",
        "goles": 1,
        "avatar": "https://minifootballleagues.com/upload/9B/7E/riclt0pf.jpg"
    },
    {
        "nombre": "Rafael Lopez Medina",
        "equipo": "Celtic Pulianas",
        "goles": 1,
        "avatar": "https://minifootballleagues.com/upload/imagesv2/avatars/Avatar_Ball_04.png"
    },
    {
        "nombre": "Juan Francisco  Camacho Roldán",
        "equipo": "Peña Fútbol Villanueva Mesia",
        "goles": 1,
        "avatar": "https://minifootballleagues.com/upload/12/A0/hd4sv1e2.jpg"
    },
    {
        "nombre": "Pablo Lorente Lavado",
        "equipo": "Ogijares 89 Fc",
        "goles": 1,
        "avatar": "https://minifootballleagues.com/upload/5F/2C/0hlyvzmi.jpg"
    }
]